mykmeansproject/__init__.py
mykmeansproject/calisan-yedek.py
mykmeansproject/kmeans-yedek.py
mykmeansproject/kmeans.py
mykmeansproject/yeni44-linux.out
mykmeansproject/yeni44-mac-arm64.out
mykmeansproject/yeni44-mac-x86_64.out
mykmeansproject/yeni44-mac.out
mykmeansproject/yeni44-windows.exe
mykmeansproject-0.7.dist-info/METADATA
mykmeansproject-0.7.dist-info/WHEEL
mykmeansproject-0.7.dist-info/top_level.txt
mykmeansproject-0.7.dist-info/RECORD
