Metadata-Version: 2.1
Name: mykmeansproject
Version: 0.7
Summary: A package for running KMeans and GeoKMeans algorithms.
Home-page: https://github.com/yourusername/mykmeansproject
Author: Vasfi Tataroglu
Author-email: vtatarog@iu.edu
Classifier: Programming Language :: Python :: 3
Classifier: License :: OSI Approved :: MIT License
Classifier: Operating System :: OS Independent
Requires-Python: >=3.6
